Metadata-Version: 1.0
Name: ofs
Version: 0.4.3
Summary: OFS - provides plugin-orientated low-level blobstore.
Home-page: http://github.com/okfn/ofs
Author: Ben O'Steen, Friedrich Lindenberg, Rufus Pollock
Author-email: bosteen@gmail.com
License: http://www.apache.org/licenses/LICENSE-2.0
Platform: UNKNOWN
